createPythonModule/CpmConst.py
createPythonModule/CreatePythonModule.py
createPythonModule/__init__.py
createPythonModule/templateData/DotGitIgnore.py
createPythonModule/templateData/SetupDotPy.py
createPythonModule/templateData/TestCaseDotPy.py
createPythonModule/templateData/TestSuiteDotPy.py
createPythonModule/templateData/__init__.py
createPythonModule-1.2.dist-info/METADATA
createPythonModule-1.2.dist-info/WHEEL
createPythonModule-1.2.dist-info/entry_points.txt
createPythonModule-1.2.dist-info/top_level.txt
createPythonModule-1.2.dist-info/RECORD
