Metadata-Version: 2.1
Name: createPythonModule
Version: 1.2
Summary: Easy generate project folder structure for Python application
Home-page: UNKNOWN
Author: Giacomo Giusti
Author-email: giacomino.giusti@gmail.com
License: UNKNOWN
Platform: UNKNOWN
Requires-Python: >3.0.0
